LICENSE
MANIFEST.in
README.rst
setup.py
vanellope/.DS_Store
vanellope/__init__.py
vanellope/app.py
vanellope/config.py
vanellope/database.py
vanellope/urls.py
vanellope.egg-info/PKG-INFO
vanellope.egg-info/SOURCES.txt
vanellope.egg-info/dependency_links.txt
vanellope.egg-info/entry_points.txt
vanellope.egg-info/requires.txt
vanellope.egg-info/top_level.txt
vanellope.egg-info/zip-safe
vanellope/.sass-cache/79718787981d86e5366a69ec5c3e3387261faf1b/_components.scssc
vanellope/.sass-cache/79718787981d86e5366a69ec5c3e3387261faf1b/_layouts.scssc
vanellope/.sass-cache/79718787981d86e5366a69ec5c3e3387261faf1b/_mixins.scssc
vanellope/.sass-cache/79718787981d86e5366a69ec5c3e3387261faf1b/_normalize.scssc
vanellope/.sass-cache/79718787981d86e5366a69ec5c3e3387261faf1b/_resets.scssc
vanellope/.sass-cache/79718787981d86e5366a69ec5c3e3387261faf1b/_variables.scssc
vanellope/.sass-cache/79718787981d86e5366a69ec5c3e3387261faf1b/style.scssc
vanellope/admin/.sass-cache/5f28f2931d04d4e60c5b24162cc489ce4a747518/_components.scssc
vanellope/admin/.sass-cache/5f28f2931d04d4e60c5b24162cc489ce4a747518/_layouts.scssc
vanellope/admin/.sass-cache/5f28f2931d04d4e60c5b24162cc489ce4a747518/_mixins.scssc
vanellope/admin/.sass-cache/5f28f2931d04d4e60c5b24162cc489ce4a747518/_normalize.scssc
vanellope/admin/.sass-cache/5f28f2931d04d4e60c5b24162cc489ce4a747518/_quill.scssc
vanellope/admin/.sass-cache/5f28f2931d04d4e60c5b24162cc489ce4a747518/_resets.scssc
vanellope/admin/.sass-cache/5f28f2931d04d4e60c5b24162cc489ce4a747518/_variables.scssc
vanellope/admin/.sass-cache/5f28f2931d04d4e60c5b24162cc489ce4a747518/admin.scssc
vanellope/admin/.sass-cache/5f28f2931d04d4e60c5b24162cc489ce4a747518/style.scssc
vanellope/admin/.sass-cache/79718787981d86e5366a69ec5c3e3387261faf1b/_components.scssc
vanellope/admin/.sass-cache/79718787981d86e5366a69ec5c3e3387261faf1b/_layouts.scssc
vanellope/admin/.sass-cache/79718787981d86e5366a69ec5c3e3387261faf1b/_mixins.scssc
vanellope/admin/.sass-cache/79718787981d86e5366a69ec5c3e3387261faf1b/_normalize.scssc
vanellope/admin/.sass-cache/79718787981d86e5366a69ec5c3e3387261faf1b/_resets.scssc
vanellope/admin/.sass-cache/79718787981d86e5366a69ec5c3e3387261faf1b/_variables.scssc
