Metadata-Version: 1.1
Name: vanellope
Version: 0.1.3
Summary: Personal publishing system
Home-page: https://github.com/qar/vanellope
Author: Qiao Anran
Author-email: qiaoanran@gmail.com
License: MIT
Platform: UNKNOWN
Classifier: Development Status :: 1 - Planning
Classifier: Environment :: Web Environment
Classifier: Intended Audience :: Developers
Classifier: License :: OSI Approved :: MIT License
Classifier: Operating System :: OS Independent
Classifier: Programming Language :: Python :: 2.7
